setup.py
bin/dsb_requests
dsb_requests/__init__.py
dsb_requests/_adapters.py
dsb_requests/_api.py
dsb_requests/_init.py
dsb_requests/_proxy.py
dsb_requests/_requests.py
dsb_requests/command.py
dsb_requests/logs.py
dsb_requests/patch_const.py
dsb_requests/tools.py
dsb_requests.egg-info/PKG-INFO
dsb_requests.egg-info/SOURCES.txt
dsb_requests.egg-info/dependency_links.txt
dsb_requests.egg-info/requires.txt
dsb_requests.egg-info/top_level.txt