Metadata-Version: 1.0
Name: dsb-requests
Version: 0.9.7
Summary: duoshoubang 's requests
Home-page: UNKNOWN
Author: tuxpy
Author-email: UNKNOWN
License: UNKNOWN
Platform: UNKNOWN
